wqrfnium_app/__init__.py
wqrfnium_app/wqrfnium_app.py
wqrfnium_app-0.1.4.dist-info/METADATA
wqrfnium_app-0.1.4.dist-info/WHEEL
wqrfnium_app-0.1.4.dist-info/top_level.txt
wqrfnium_app-0.1.4.dist-info/RECORD
