Metadata-Version: 2.1
Name: wqrfnium-app
Version: 0.1.4
Summary: to fix the appium error which caused by ui change,wqrfnium_app can find element!
Home-page: https://github.com/Woqurefan/
Author: wqrf
Author-email: 1074321997@qq.com
License: MIT
Keywords: wqrf
Platform: UNKNOWN
